{
  "name": "ptaltsvUWIi",
  "session": "baudy_p@hotmail.fr:Mogwai16641664$",
  "uuid": "4801b837-b0de-462f-ba51-835e12c6682a",
  "ban_status": {
    "hypixel": "unknown",
    "donut": "unknown",
    "cubecraft": "unknown",
    "is_unbanned": false,
    "display": "All Banned"
  },
  "log_time": "2026/01/21-13:45",
  "full_message": {
    "type": 0,
    "content": "",
    "mentions": [],
    "mention_roles": [],
    "attachments": [],
    "embeds": [
      {
        "type": "rich",
        "title": "`ptaltsvUWIi`",
        "description": "||```baudy_p@hotmail.fr:Mogwai16641664$```||\n[**RECOMMENDED: use accesstoken instead! (click)**](https://tklogin.villainsrule.xyz/)\n\n**Hypixel Status:** `UNBANNED`\n> Joined successfully\n**DonutSMP Status:** `UNKNOWN`\n> Proxy timeout\n**CubeCraft Status:** `UNBANNED`\n> Joined successfully\n\n**Account Info:**\nUUID: `4801b837-b0de-462f-ba51-835e12c6682a`\nGame Pass Account: `GAMEPASS ULTIMATE`\nMinecraft Capes: `Pan, Common`\nOptifine Cape: `No`\nName Changeable: `No`\nAccount Creation Date: <t:1768940334:F>\nOther Games: `Minecraft Dungeons, Minecraft Bedrock, Minecraft Legends`\n\n*No cap — the rare stuff hides in premium. `/premium generate`.*",
        "color": 65280,
        "timestamp": "2026-01-21T05:45:04.779000+00:00",
        "author": {
          "name": "369575/429258 | 230"
        },
        "thumbnail": {
          "url": "https://mc-heads.net/body/4801b837-b0de-462f-ba51-835e12c6682a/100/left",
          "proxy_url": "https://images-ext-1.discordapp.net/external/R5M_rTR7PZK5IzaV4SGwoiyOLBDDpt3ahWnfLmkuRwc/https/mc-heads.net/body/4801b837-b0de-462f-ba51-835e12c6682a/100/left",
          "width": 100,
          "height": 240,
          "content_type": "image/png",
          "placeholder": "kyiKEgQrL3JLhadrdbBWBwZYiXmBVWY=",
          "placeholder_version": 1,
          "flags": 0
        },
        "footer": {
          "text": "discord.gg/logs",
          "icon_url": "https://media.forgecdn.net/avatars/thumbnails/242/321/256/256/637133550294159539_animated.gif",
          "proxy_icon_url": "https://images-ext-1.discordapp.net/external/f2wHhCuANqVMKBMmMrHpQemP5OFqNiSicwCP1Bqa5Fs/https/media.forgecdn.net/avatars/thumbnails/242/321/256/256/637133550294159539_animated.gif"
        },
        "content_scan_version": 3
      }
    ],
    "timestamp": "2026-01-21T05:45:04.951000+00:00",
    "edited_timestamp": null,
    "flags": 4096,
    "components": [
      {
        "type": 1,
        "id": 1,
        "components": [
          {
            "type": 2,
            "id": 2,
            "custom_id": "credentials_cmknlml9o05pvhiejwi3p3pst",
            "style": 3,
            "label": "Get Credentials",
            "emoji": {
              "name": "🔑"
            }
          }
        ]
      }
    ],
    "id": "1463409044151734274",
    "channel_id": "1463352414944887001",
    "author": {
      "id": "1435331490002112522",
      "username": "DiscoveryService",
      "avatar": "a0dd60da241a644266b65e78afc078da",
      "discriminator": "5784",
      "public_flags": 0,
      "flags": 0,
      "bot": true,
      "banner": null,
      "accent_color": null,
      "global_name": null,
      "avatar_decoration_data": null,
      "collectibles": null,
      "display_name_styles": null,
      "banner_color": null,
      "clan": null,
      "primary_guild": null
    },
    "pinned": false,
    "mention_everyone": false,
    "tts": false
  }
}