{
  "name": "DaxelinOnDcEBOQQ",
  "session": "larkin.anderson22@gmail.com:Vedder04!",
  "uuid": "6adae102-0447-4a3f-81c2-9bc4a6a538f5",
  "hypixel": "unknown",
  "log_time": "2026/01/09-19:01",
  "full_message": {
    "type": 0,
    "content": "",
    "mentions": [],
    "mention_roles": [],
    "attachments": [],
    "embeds": [
      {
        "type": "rich",
        "title": "`DaxelinOnDcEBOQQ`",
        "description": "||```larkin.anderson22@gmail.com:Vedder04!```||\n[**RECOMMENDED: use accesstoken instead! (click)**](https://tklogin.villainsrule.xyz/)\n\n**Hypixel Status:** `BANNED`\n> You are temporarily banned for 22d 14h 59m 26s from this server!\n> Reason: Cheating through the use of unfair game advantages.\n**DonutSMP Status:** `BANNED`\n> You are banned for botting DonutSMP.\n**CubeCraft Status:** `UNBANNED`\n> Joined successfully\n\n**Hypixel General Info:**\nLevel: `10.84`\nFirst Login: <t:1693867980:F>\nLast Login: <t:1767319080:F>\nBedWars Stars: `6`\n\n**DonutSMP Info:**\nPlaytime: `0d 1h 6m`\nShards: `587`\n\n**Account Info:**\nUUID: `6adae102-0447-4a3f-81c2-9bc4a6a538f5`\nMinecraft Capes: `Pan, Common`\nOptifine Cape: `No`\nName Changeable: `No`\nAccount Creation Date: <t:1693867717:F>\nOther Games: `Minecraft Bedrock`\n\n*Want the private stuff? `/premium generate` — lasts 12h or forever if you boost.*",
        "color": 10175221,
        "timestamp": "2026-01-09T11:01:46.863000+00:00",
        "author": {
          "name": "19723/211540 | 1"
        },
        "thumbnail": {
          "url": "https://mc-heads.net/body/6adae102-0447-4a3f-81c2-9bc4a6a538f5/100/left",
          "proxy_url": "https://images-ext-1.discordapp.net/external/kGuaewJPgqy2zNXWBwi86RNWHAp5w4R9lAw5ctcz_LI/https/mc-heads.net/body/6adae102-0447-4a3f-81c2-9bc4a6a538f5/100/left",
          "width": 100,
          "height": 240,
          "content_type": "image/png",
          "placeholder": "EhiGAgIrSG/DhhgPnsTyaAZYiXmBVWY=",
          "placeholder_version": 1,
          "flags": 0
        },
        "footer": {
          "text": "discord.gg/logs",
          "icon_url": "https://media.forgecdn.net/avatars/thumbnails/242/321/256/256/637133550294159539_animated.gif",
          "proxy_icon_url": "https://images-ext-1.discordapp.net/external/f2wHhCuANqVMKBMmMrHpQemP5OFqNiSicwCP1Bqa5Fs/https/media.forgecdn.net/avatars/thumbnails/242/321/256/256/637133550294159539_animated.gif"
        },
        "content_scan_version": 3
      }
    ],
    "timestamp": "2026-01-09T11:01:47.504000+00:00",
    "edited_timestamp": null,
    "flags": 4096,
    "components": [
      {
        "type": 1,
        "id": 1,
        "components": [
          {
            "type": 2,
            "id": 2,
            "custom_id": "credentials_cmk6rnnix05yzhi9cjdp4gtid",
            "style": 3,
            "label": "Get Credentials",
            "emoji": {
              "name": "🔑"
            }
          }
        ]
      }
    ],
    "id": "1459140092248457331",
    "channel_id": "1459003783051874458",
    "author": {
      "id": "1435331490002112522",
      "username": "DiscoveryService",
      "avatar": "a0dd60da241a644266b65e78afc078da",
      "discriminator": "5784",
      "public_flags": 0,
      "flags": 0,
      "bot": true,
      "banner": null,
      "accent_color": null,
      "global_name": null,
      "avatar_decoration_data": null,
      "collectibles": null,
      "display_name_styles": null,
      "banner_color": null,
      "clan": null,
      "primary_guild": null
    },
    "pinned": false,
    "mention_everyone": false,
    "tts": false
  }
}